WignerSymbol.cpython-39-i386-linux-gnu.so
WignerSymbol-0.1.2.dist-info/RECORD
WignerSymbol-0.1.2.dist-info/top_level.txt
WignerSymbol-0.1.2.dist-info/LICENSE
WignerSymbol-0.1.2.dist-info/WHEEL
WignerSymbol-0.1.2.dist-info/METADATA
